{"nodes": [{"id": "src_main_java_com_payroll_system_repository_payrollrepositoryimpl_java", "label": "PayrollRepositoryImpl.java", "file_type": "code", "source_file": "src\\main\\java\\com\\payroll\\system\\repository\\PayrollRepositoryImpl.java", "source_location": "L1"}, {"id": "payrollrepositoryimpl_payrollrepositoryimpl", "label": "PayrollRepositoryImpl", "file_type": "code", "source_file": "src\\main\\java\\com\\payroll\\system\\repository\\PayrollRepositoryImpl.java", "source_location": "L27"}, {"id": "payrollrepositoryimpl_payrollrepositoryimpl_savepayrollresult", "label": ".savePayrollResult()", "file_type": "code", "source_file": "src\\main\\java\\com\\payroll\\system\\repository\\PayrollRepositoryImpl.java", "source_location": "L31"}, {"id": "payrollrepositoryimpl_payrollrepositoryimpl_logprocessingerror", "label": ".logProcessingError()", "file_type": "code", "source_file": "src\\main\\java\\com\\payroll\\system\\repository\\PayrollRepositoryImpl.java", "source_location": "L65"}, {"id": "payrollrepositoryimpl_payrollrepositoryimpl_getallactiveemployeeids", "label": ".getAllActiveEmployeeIDs()", "file_type": "code", "source_file": "src\\main\\java\\com\\payroll\\system\\repository\\PayrollRepositoryImpl.java", "source_location": "L88"}, {"id": "payrollrepositoryimpl_payrollrepositoryimpl_fetchemployeedata", "label": ".fetchEmployeeData()", "file_type": "code", "source_file": "src\\main\\java\\com\\payroll\\system\\repository\\PayrollRepositoryImpl.java", "source_location": "L111"}, {"id": "payrollrepositoryimpl_payrollrepositoryimpl_openconnection", "label": ".openConnection()", "file_type": "code", "source_file": "src\\main\\java\\com\\payroll\\system\\repository\\PayrollRepositoryImpl.java", "source_location": "L197"}, {"id": "payrollrepositoryimpl_payrollrepositoryimpl_mapemployee", "label": ".mapEmployee()", "file_type": "code", "source_file": "src\\main\\java\\com\\payroll\\system\\repository\\PayrollRepositoryImpl.java", "source_location": "L201"}, {"id": "payrollrepositoryimpl_payrollrepositoryimpl_mapattendance", "label": ".mapAttendance()", "file_type": "code", "source_file": "src\\main\\java\\com\\payroll\\system\\repository\\PayrollRepositoryImpl.java", "source_location": "L214"}, {"id": "payrollrepositoryimpl_payrollrepositoryimpl_mapfinancials", "label": ".mapFinancials()", "file_type": "code", "source_file": "src\\main\\java\\com\\payroll\\system\\repository\\PayrollRepositoryImpl.java", "source_location": "L224"}, {"id": "payrollrepositoryimpl_payrollrepositoryimpl_maptaxcontext", "label": ".mapTaxContext()", "file_type": "code", "source_file": "src\\main\\java\\com\\payroll\\system\\repository\\PayrollRepositoryImpl.java", "source_location": "L233"}, {"id": "payrollrepositoryimpl_payrollrepositoryimpl_coalesce", "label": ".coalesce()", "file_type": "code", "source_file": "src\\main\\java\\com\\payroll\\system\\repository\\PayrollRepositoryImpl.java", "source_location": "L248"}, {"id": "payrollrepositoryimpl_payrollrepositoryimpl_ensurepayrollresultstable", "label": ".ensurePayrollResultsTable()", "file_type": "code", "source_file": "src\\main\\java\\com\\payroll\\system\\repository\\PayrollRepositoryImpl.java", "source_location": "L257"}, {"id": "payrollrepositoryimpl_payrollrepositoryimpl_ensurepayrollaudittable", "label": ".ensurePayrollAuditTable()", "file_type": "code", "source_file": "src\\main\\java\\com\\payroll\\system\\repository\\PayrollRepositoryImpl.java", "source_location": "L277"}, {"id": "payrollrepositoryimpl_payrollrepositoryimpl_gettablecolumns", "label": ".getTableColumns()", "file_type": "code", "source_file": "src\\main\\java\\com\\payroll\\system\\repository\\PayrollRepositoryImpl.java", "source_location": "L292"}, {"id": "payrollrepositoryimpl_payrollrepositoryimpl_putifpresent", "label": ".putIfPresent()", "file_type": "code", "source_file": "src\\main\\java\\com\\payroll\\system\\repository\\PayrollRepositoryImpl.java", "source_location": "L303"}, {"id": "payrollrepositoryimpl_payrollrepositoryimpl_buildinsertsql", "label": ".buildInsertSql()", "file_type": "code", "source_file": "src\\main\\java\\com\\payroll\\system\\repository\\PayrollRepositoryImpl.java", "source_location": "L312"}], "edges": [{"source": "src_main_java_com_payroll_system_repository_payrollrepositoryimpl_java", "target": "attendancedto", "relation": "imports", "confidence": "EXTRACTED", "source_file": "src\\main\\java\\com\\payroll\\system\\repository\\PayrollRepositoryImpl.java", "source_location": "L3", "weight": 1.0}, {"source": "src_main_java_com_payroll_system_repository_payrollrepositoryimpl_java", "target": "employeedto", "relation": "imports", "confidence": "EXTRACTED", "source_file": "src\\main\\java\\com\\payroll\\system\\repository\\PayrollRepositoryImpl.java", "source_location": "L4", "weight": 1.0}, {"source": "src_main_java_com_payroll_system_repository_payrollrepositoryimpl_java", "target": "financialsdto", "relation": "imports", "confidence": "EXTRACTED", "source_file": "src\\main\\java\\com\\payroll\\system\\repository\\PayrollRepositoryImpl.java", "source_location": "L5", "weight": 1.0}, {"source": "src_main_java_com_payroll_system_repository_payrollrepositoryimpl_java", "target": "ipayrollrepository", "relation": "imports", "confidence": "EXTRACTED", "source_file": "src\\main\\java\\com\\payroll\\system\\repository\\PayrollRepositoryImpl.java", "source_location": "L6", "weight": 1.0}, {"source": "src_main_java_com_payroll_system_repository_payrollrepositoryimpl_java", "target": "payrolldatapackage", "relation": "imports", "confidence": "EXTRACTED", "source_file": "src\\main\\java\\com\\payroll\\system\\repository\\PayrollRepositoryImpl.java", "source_location": "L7", "weight": 1.0}, {"source": "src_main_java_com_payroll_system_repository_payrollrepositoryimpl_java", "target": "payrollresultdto", "relation": "imports", "confidence": "EXTRACTED", "source_file": "src\\main\\java\\com\\payroll\\system\\repository\\PayrollRepositoryImpl.java", "source_location": "L8", "weight": 1.0}, {"source": "src_main_java_com_payroll_system_repository_payrollrepositoryimpl_java", "target": "taxcontextdto", "relation": "imports", "confidence": "EXTRACTED", "source_file": "src\\main\\java\\com\\payroll\\system\\repository\\PayrollRepositoryImpl.java", "source_location": "L9", "weight": 1.0}, {"source": "src_main_java_com_payroll_system_repository_payrollrepositoryimpl_java", "target": "connection", "relation": "imports", "confidence": "EXTRACTED", "source_file": "src\\main\\java\\com\\payroll\\system\\repository\\PayrollRepositoryImpl.java", "source_location": "L11", "weight": 1.0}, {"source": "src_main_java_com_payroll_system_repository_payrollrepositoryimpl_java", "target": "drivermanager", "relation": "imports", "confidence": "EXTRACTED", "source_file": "src\\main\\java\\com\\payroll\\system\\repository\\PayrollRepositoryImpl.java", "source_location": "L12", "weight": 1.0}, {"source": "src_main_java_com_payroll_system_repository_payrollrepositoryimpl_java", "target": "preparedstatement", "relation": "imports", "confidence": "EXTRACTED", "source_file": "src\\main\\java\\com\\payroll\\system\\repository\\PayrollRepositoryImpl.java", "source_location": "L13", "weight": 1.0}, {"source": "src_main_java_com_payroll_system_repository_payrollrepositoryimpl_java", "target": "resultset", "relation": "imports", "confidence": "EXTRACTED", "source_file": "src\\main\\java\\com\\payroll\\system\\repository\\PayrollRepositoryImpl.java", "source_location": "L14", "weight": 1.0}, {"source": "src_main_java_com_payroll_system_repository_payrollrepositoryimpl_java", "target": "sqlexception", "relation": "imports", "confidence": "EXTRACTED", "source_file": "src\\main\\java\\com\\payroll\\system\\repository\\PayrollRepositoryImpl.java", "source_location": "L15", "weight": 1.0}, {"source": "src_main_java_com_payroll_system_repository_payrollrepositoryimpl_java", "target": "statement", "relation": "imports", "confidence": "EXTRACTED", "source_file": "src\\main\\java\\com\\payroll\\system\\repository\\PayrollRepositoryImpl.java", "source_location": "L16", "weight": 1.0}, {"source": "src_main_java_com_payroll_system_repository_payrollrepositoryimpl_java", "target": "timestamp", "relation": "imports", "confidence": "EXTRACTED", "source_file": "src\\main\\java\\com\\payroll\\system\\repository\\PayrollRepositoryImpl.java", "source_location": "L17", "weight": 1.0}, {"source": "src_main_java_com_payroll_system_repository_payrollrepositoryimpl_java", "target": "instant", "relation": "imports", "confidence": "EXTRACTED", "source_file": "src\\main\\java\\com\\payroll\\system\\repository\\PayrollRepositoryImpl.java", "source_location": "L18", "weight": 1.0}, {"source": "src_main_java_com_payroll_system_repository_payrollrepositoryimpl_java", "target": "arraylist", "relation": "imports", "confidence": "EXTRACTED", "source_file": "src\\main\\java\\com\\payroll\\system\\repository\\PayrollRepositoryImpl.java", "source_location": "L19", "weight": 1.0}, {"source": "src_main_java_com_payroll_system_repository_payrollrepositoryimpl_java", "target": "linkedhashmap", "relation": "imports", "confidence": "EXTRACTED", "source_file": "src\\main\\java\\com\\payroll\\system\\repository\\PayrollRepositoryImpl.java", "source_location": "L20", "weight": 1.0}, {"source": "src_main_java_com_payroll_system_repository_payrollrepositoryimpl_java", "target": "list", "relation": "imports", "confidence": "EXTRACTED", "source_file": "src\\main\\java\\com\\payroll\\system\\repository\\PayrollRepositoryImpl.java", "source_location": "L21", "weight": 1.0}, {"source": "src_main_java_com_payroll_system_repository_payrollrepositoryimpl_java", "target": "locale", "relation": "imports", "confidence": "EXTRACTED", "source_file": "src\\main\\java\\com\\payroll\\system\\repository\\PayrollRepositoryImpl.java", "source_location": "L22", "weight": 1.0}, {"source": "src_main_java_com_payroll_system_repository_payrollrepositoryimpl_java", "target": "map", "relation": "imports", "confidence": "EXTRACTED", "source_file": "src\\main\\java\\com\\payroll\\system\\repository\\PayrollRepositoryImpl.java", "source_location": "L23", "weight": 1.0}, {"source": "src_main_java_com_payroll_system_repository_payrollrepositoryimpl_java", "target": "set", "relation": "imports", "confidence": "EXTRACTED", "source_file": "src\\main\\java\\com\\payroll\\system\\repository\\PayrollRepositoryImpl.java", "source_location": "L24", "weight": 1.0}, {"source": "src_main_java_com_payroll_system_repository_payrollrepositoryimpl_java", "target": "hashset", "relation": "imports", "confidence": "EXTRACTED", "source_file": "src\\main\\java\\com\\payroll\\system\\repository\\PayrollRepositoryImpl.java", "source_location": "L25", "weight": 1.0}, {"source": "src_main_java_com_payroll_system_repository_payrollrepositoryimpl_java", "target": "payrollrepositoryimpl_payrollrepositoryimpl", "relation": "contains", "confidence": "EXTRACTED", "source_file": "src\\main\\java\\com\\payroll\\system\\repository\\PayrollRepositoryImpl.java", "source_location": "L27", "weight": 1.0}, {"source": "payrollrepositoryimpl_payrollrepositoryimpl", "target": "payrollrepositoryimpl_payrollrepositoryimpl_savepayrollresult", "relation": "method", "confidence": "EXTRACTED", "source_file": "src\\main\\java\\com\\payroll\\system\\repository\\PayrollRepositoryImpl.java", "source_location": "L31", "weight": 1.0}, {"source": "payrollrepositoryimpl_payrollrepositoryimpl", "target": "payrollrepositoryimpl_payrollrepositoryimpl_logprocessingerror", "relation": "method", "confidence": "EXTRACTED", "source_file": "src\\main\\java\\com\\payroll\\system\\repository\\PayrollRepositoryImpl.java", "source_location": "L65", "weight": 1.0}, {"source": "payrollrepositoryimpl_payrollrepositoryimpl", "target": "payrollrepositoryimpl_payrollrepositoryimpl_getallactiveemployeeids", "relation": "method", "confidence": "EXTRACTED", "source_file": "src\\main\\java\\com\\payroll\\system\\repository\\PayrollRepositoryImpl.java", "source_location": "L88", "weight": 1.0}, {"source": "payrollrepositoryimpl_payrollrepositoryimpl", "target": "payrollrepositoryimpl_payrollrepositoryimpl_fetchemployeedata", "relation": "method", "confidence": "EXTRACTED", "source_file": "src\\main\\java\\com\\payroll\\system\\repository\\PayrollRepositoryImpl.java", "source_location": "L111", "weight": 1.0}, {"source": "payrollrepositoryimpl_payrollrepositoryimpl", "target": "payrollrepositoryimpl_payrollrepositoryimpl_openconnection", "relation": "method", "confidence": "EXTRACTED", "source_file": "src\\main\\java\\com\\payroll\\system\\repository\\PayrollRepositoryImpl.java", "source_location": "L197", "weight": 1.0}, {"source": "payrollrepositoryimpl_payrollrepositoryimpl", "target": "payrollrepositoryimpl_payrollrepositoryimpl_mapemployee", "relation": "method", "confidence": "EXTRACTED", "source_file": "src\\main\\java\\com\\payroll\\system\\repository\\PayrollRepositoryImpl.java", "source_location": "L201", "weight": 1.0}, {"source": "payrollrepositoryimpl_payrollrepositoryimpl", "target": "payrollrepositoryimpl_payrollrepositoryimpl_mapattendance", "relation": "method", "confidence": "EXTRACTED", "source_file": "src\\main\\java\\com\\payroll\\system\\repository\\PayrollRepositoryImpl.java", "source_location": "L214", "weight": 1.0}, {"source": "payrollrepositoryimpl_payrollrepositoryimpl", "target": "payrollrepositoryimpl_payrollrepositoryimpl_mapfinancials", "relation": "method", "confidence": "EXTRACTED", "source_file": "src\\main\\java\\com\\payroll\\system\\repository\\PayrollRepositoryImpl.java", "source_location": "L224", "weight": 1.0}, {"source": "payrollrepositoryimpl_payrollrepositoryimpl", "target": "payrollrepositoryimpl_payrollrepositoryimpl_maptaxcontext", "relation": "method", "confidence": "EXTRACTED", "source_file": "src\\main\\java\\com\\payroll\\system\\repository\\PayrollRepositoryImpl.java", "source_location": "L233", "weight": 1.0}, {"source": "payrollrepositoryimpl_payrollrepositoryimpl", "target": "payrollrepositoryimpl_payrollrepositoryimpl_coalesce", "relation": "method", "confidence": "EXTRACTED", "source_file": "src\\main\\java\\com\\payroll\\system\\repository\\PayrollRepositoryImpl.java", "source_location": "L248", "weight": 1.0}, {"source": "payrollrepositoryimpl_payrollrepositoryimpl", "target": "payrollrepositoryimpl_payrollrepositoryimpl_ensurepayrollresultstable", "relation": "method", "confidence": "EXTRACTED", "source_file": "src\\main\\java\\com\\payroll\\system\\repository\\PayrollRepositoryImpl.java", "source_location": "L257", "weight": 1.0}, {"source": "payrollrepositoryimpl_payrollrepositoryimpl", "target": "payrollrepositoryimpl_payrollrepositoryimpl_ensurepayrollaudittable", "relation": "method", "confidence": "EXTRACTED", "source_file": "src\\main\\java\\com\\payroll\\system\\repository\\PayrollRepositoryImpl.java", "source_location": "L277", "weight": 1.0}, {"source": "payrollrepositoryimpl_payrollrepositoryimpl", "target": "payrollrepositoryimpl_payrollrepositoryimpl_gettablecolumns", "relation": "method", "confidence": "EXTRACTED", "source_file": "src\\main\\java\\com\\payroll\\system\\repository\\PayrollRepositoryImpl.java", "source_location": "L292", "weight": 1.0}, {"source": "payrollrepositoryimpl_payrollrepositoryimpl", "target": "payrollrepositoryimpl_payrollrepositoryimpl_putifpresent", "relation": "method", "confidence": "EXTRACTED", "source_file": "src\\main\\java\\com\\payroll\\system\\repository\\PayrollRepositoryImpl.java", "source_location": "L303", "weight": 1.0}, {"source": "payrollrepositoryimpl_payrollrepositoryimpl", "target": "payrollrepositoryimpl_payrollrepositoryimpl_buildinsertsql", "relation": "method", "confidence": "EXTRACTED", "source_file": "src\\main\\java\\com\\payroll\\system\\repository\\PayrollRepositoryImpl.java", "source_location": "L312", "weight": 1.0}, {"source": "payrollrepositoryimpl_payrollrepositoryimpl_savepayrollresult", "target": "payrollrepositoryimpl_payrollrepositoryimpl_openconnection", "relation": "calls", "confidence": "EXTRACTED", "source_file": "src\\main\\java\\com\\payroll\\system\\repository\\PayrollRepositoryImpl.java", "source_location": "L33", "weight": 1.0}, {"source": "payrollrepositoryimpl_payrollrepositoryimpl_savepayrollresult", "target": "payrollrepositoryimpl_payrollrepositoryimpl_ensurepayrollresultstable", "relation": "calls", "confidence": "EXTRACTED", "source_file": "src\\main\\java\\com\\payroll\\system\\repository\\PayrollRepositoryImpl.java", "source_location": "L34", "weight": 1.0}, {"source": "payrollrepositoryimpl_payrollrepositoryimpl_savepayrollresult", "target": "payrollrepositoryimpl_payrollrepositoryimpl_gettablecolumns", "relation": "calls", "confidence": "EXTRACTED", "source_file": "src\\main\\java\\com\\payroll\\system\\repository\\PayrollRepositoryImpl.java", "source_location": "L35", "weight": 1.0}, {"source": "payrollrepositoryimpl_payrollrepositoryimpl_savepayrollresult", "target": "payrollrepositoryimpl_payrollrepositoryimpl_putifpresent", "relation": "calls", "confidence": "EXTRACTED", "source_file": "src\\main\\java\\com\\payroll\\system\\repository\\PayrollRepositoryImpl.java", "source_location": "L38", "weight": 1.0}, {"source": "payrollrepositoryimpl_payrollrepositoryimpl_savepayrollresult", "target": "payrollrepositoryimpl_payrollrepositoryimpl_buildinsertsql", "relation": "calls", "confidence": "EXTRACTED", "source_file": "src\\main\\java\\com\\payroll\\system\\repository\\PayrollRepositoryImpl.java", "source_location": "L50", "weight": 1.0}, {"source": "payrollrepositoryimpl_payrollrepositoryimpl_logprocessingerror", "target": "payrollrepositoryimpl_payrollrepositoryimpl_openconnection", "relation": "calls", "confidence": "EXTRACTED", "source_file": "src\\main\\java\\com\\payroll\\system\\repository\\PayrollRepositoryImpl.java", "source_location": "L72", "weight": 1.0}, {"source": "payrollrepositoryimpl_payrollrepositoryimpl_logprocessingerror", "target": "payrollrepositoryimpl_payrollrepositoryimpl_ensurepayrollaudittable", "relation": "calls", "confidence": "EXTRACTED", "source_file": "src\\main\\java\\com\\payroll\\system\\repository\\PayrollRepositoryImpl.java", "source_location": "L73", "weight": 1.0}, {"source": "payrollrepositoryimpl_payrollrepositoryimpl_getallactiveemployeeids", "target": "payrollrepositoryimpl_payrollrepositoryimpl_openconnection", "relation": "calls", "confidence": "EXTRACTED", "source_file": "src\\main\\java\\com\\payroll\\system\\repository\\PayrollRepositoryImpl.java", "source_location": "L98", "weight": 1.0}, {"source": "payrollrepositoryimpl_payrollrepositoryimpl_fetchemployeedata", "target": "payrollrepositoryimpl_payrollrepositoryimpl_openconnection", "relation": "calls", "confidence": "EXTRACTED", "source_file": "src\\main\\java\\com\\payroll\\system\\repository\\PayrollRepositoryImpl.java", "source_location": "L169", "weight": 1.0}, {"source": "payrollrepositoryimpl_payrollrepositoryimpl_fetchemployeedata", "target": "payrollrepositoryimpl_payrollrepositoryimpl_mapemployee", "relation": "calls", "confidence": "EXTRACTED", "source_file": "src\\main\\java\\com\\payroll\\system\\repository\\PayrollRepositoryImpl.java", "source_location": "L184", "weight": 1.0}, {"source": "payrollrepositoryimpl_payrollrepositoryimpl_fetchemployeedata", "target": "payrollrepositoryimpl_payrollrepositoryimpl_mapattendance", "relation": "calls", "confidence": "EXTRACTED", "source_file": "src\\main\\java\\com\\payroll\\system\\repository\\PayrollRepositoryImpl.java", "source_location": "L185", "weight": 1.0}, {"source": "payrollrepositoryimpl_payrollrepositoryimpl_fetchemployeedata", "target": "payrollrepositoryimpl_payrollrepositoryimpl_mapfinancials", "relation": "calls", "confidence": "EXTRACTED", "source_file": "src\\main\\java\\com\\payroll\\system\\repository\\PayrollRepositoryImpl.java", "source_location": "L186", "weight": 1.0}, {"source": "payrollrepositoryimpl_payrollrepositoryimpl_fetchemployeedata", "target": "payrollrepositoryimpl_payrollrepositoryimpl_maptaxcontext", "relation": "calls", "confidence": "EXTRACTED", "source_file": "src\\main\\java\\com\\payroll\\system\\repository\\PayrollRepositoryImpl.java", "source_location": "L187", "weight": 1.0}, {"source": "payrollrepositoryimpl_payrollrepositoryimpl_maptaxcontext", "target": "payrollrepositoryimpl_payrollrepositoryimpl_coalesce", "relation": "calls", "confidence": "EXTRACTED", "source_file": "src\\main\\java\\com\\payroll\\system\\repository\\PayrollRepositoryImpl.java", "source_location": "L235", "weight": 1.0}], "raw_calls": [{"caller_nid": "payrollrepositoryimpl_payrollrepositoryimpl_savepayrollresult", "callee": "from", "source_file": "src\\main\\java\\com\\payroll\\system\\repository\\PayrollRepositoryImpl.java", "source_location": "L48"}, {"caller_nid": "payrollrepositoryimpl_payrollrepositoryimpl_savepayrollresult", "callee": "now", "source_file": "src\\main\\java\\com\\payroll\\system\\repository\\PayrollRepositoryImpl.java", "source_location": "L48"}, {"caller_nid": "payrollrepositoryimpl_payrollrepositoryimpl_savepayrollresult", "callee": "prepareStatement", "source_file": "src\\main\\java\\com\\payroll\\system\\repository\\PayrollRepositoryImpl.java", "source_location": "L51"}, {"caller_nid": "payrollrepositoryimpl_payrollrepositoryimpl_savepayrollresult", "callee": "values", "source_file": "src\\main\\java\\com\\payroll\\system\\repository\\PayrollRepositoryImpl.java", "source_location": "L53"}, {"caller_nid": "payrollrepositoryimpl_payrollrepositoryimpl_savepayrollresult", "callee": "setObject", "source_file": "src\\main\\java\\com\\payroll\\system\\repository\\PayrollRepositoryImpl.java", "source_location": "L54"}, {"caller_nid": "payrollrepositoryimpl_payrollrepositoryimpl_savepayrollresult", "callee": "executeUpdate", "source_file": "src\\main\\java\\com\\payroll\\system\\repository\\PayrollRepositoryImpl.java", "source_location": "L56"}, {"caller_nid": "payrollrepositoryimpl_payrollrepositoryimpl_savepayrollresult", "callee": "printf", "source_file": "src\\main\\java\\com\\payroll\\system\\repository\\PayrollRepositoryImpl.java", "source_location": "L59"}, {"caller_nid": "payrollrepositoryimpl_payrollrepositoryimpl_savepayrollresult", "callee": "getMessage", "source_file": "src\\main\\java\\com\\payroll\\system\\repository\\PayrollRepositoryImpl.java", "source_location": "L60"}, {"caller_nid": "payrollrepositoryimpl_payrollrepositoryimpl_logprocessingerror", "callee": "prepareStatement", "source_file": "src\\main\\java\\com\\payroll\\system\\repository\\PayrollRepositoryImpl.java", "source_location": "L74"}, {"caller_nid": "payrollrepositoryimpl_payrollrepositoryimpl_logprocessingerror", "callee": "setString", "source_file": "src\\main\\java\\com\\payroll\\system\\repository\\PayrollRepositoryImpl.java", "source_location": "L75"}, {"caller_nid": "payrollrepositoryimpl_payrollrepositoryimpl_logprocessingerror", "callee": "setString", "source_file": "src\\main\\java\\com\\payroll\\system\\repository\\PayrollRepositoryImpl.java", "source_location": "L76"}, {"caller_nid": "payrollrepositoryimpl_payrollrepositoryimpl_logprocessingerror", "callee": "setString", "source_file": "src\\main\\java\\com\\payroll\\system\\repository\\PayrollRepositoryImpl.java", "source_location": "L77"}, {"caller_nid": "payrollrepositoryimpl_payrollrepositoryimpl_logprocessingerror", "callee": "setString", "source_file": "src\\main\\java\\com\\payroll\\system\\repository\\PayrollRepositoryImpl.java", "source_location": "L78"}, {"caller_nid": "payrollrepositoryimpl_payrollrepositoryimpl_logprocessingerror", "callee": "setTimestamp", "source_file": "src\\main\\java\\com\\payroll\\system\\repository\\PayrollRepositoryImpl.java", "source_location": "L79"}, {"caller_nid": "payrollrepositoryimpl_payrollrepositoryimpl_logprocessingerror", "callee": "from", "source_file": "src\\main\\java\\com\\payroll\\system\\repository\\PayrollRepositoryImpl.java", "source_location": "L79"}, {"caller_nid": "payrollrepositoryimpl_payrollrepositoryimpl_logprocessingerror", "callee": "now", "source_file": "src\\main\\java\\com\\payroll\\system\\repository\\PayrollRepositoryImpl.java", "source_location": "L79"}, {"caller_nid": "payrollrepositoryimpl_payrollrepositoryimpl_logprocessingerror", "callee": "executeUpdate", "source_file": "src\\main\\java\\com\\payroll\\system\\repository\\PayrollRepositoryImpl.java", "source_location": "L80"}, {"caller_nid": "payrollrepositoryimpl_payrollrepositoryimpl_logprocessingerror", "callee": "printf", "source_file": "src\\main\\java\\com\\payroll\\system\\repository\\PayrollRepositoryImpl.java", "source_location": "L83"}, {"caller_nid": "payrollrepositoryimpl_payrollrepositoryimpl_getallactiveemployeeids", "callee": "prepareStatement", "source_file": "src\\main\\java\\com\\payroll\\system\\repository\\PayrollRepositoryImpl.java", "source_location": "L99"}, {"caller_nid": "payrollrepositoryimpl_payrollrepositoryimpl_getallactiveemployeeids", "callee": "executeQuery", "source_file": "src\\main\\java\\com\\payroll\\system\\repository\\PayrollRepositoryImpl.java", "source_location": "L100"}, {"caller_nid": "payrollrepositoryimpl_payrollrepositoryimpl_getallactiveemployeeids", "callee": "next", "source_file": "src\\main\\java\\com\\payroll\\system\\repository\\PayrollRepositoryImpl.java", "source_location": "L102"}, {"caller_nid": "payrollrepositoryimpl_payrollrepositoryimpl_getallactiveemployeeids", "callee": "add", "source_file": "src\\main\\java\\com\\payroll\\system\\repository\\PayrollRepositoryImpl.java", "source_location": "L103"}, {"caller_nid": "payrollrepositoryimpl_payrollrepositoryimpl_getallactiveemployeeids", "callee": "getString", "source_file": "src\\main\\java\\com\\payroll\\system\\repository\\PayrollRepositoryImpl.java", "source_location": "L103"}, {"caller_nid": "payrollrepositoryimpl_payrollrepositoryimpl_getallactiveemployeeids", "callee": "printf", "source_file": "src\\main\\java\\com\\payroll\\system\\repository\\PayrollRepositoryImpl.java", "source_location": "L106"}, {"caller_nid": "payrollrepositoryimpl_payrollrepositoryimpl_getallactiveemployeeids", "callee": "getMessage", "source_file": "src\\main\\java\\com\\payroll\\system\\repository\\PayrollRepositoryImpl.java", "source_location": "L106"}, {"caller_nid": "payrollrepositoryimpl_payrollrepositoryimpl_fetchemployeedata", "callee": "prepareStatement", "source_file": "src\\main\\java\\com\\payroll\\system\\repository\\PayrollRepositoryImpl.java", "source_location": "L170"}, {"caller_nid": "payrollrepositoryimpl_payrollrepositoryimpl_fetchemployeedata", "callee": "setString", "source_file": "src\\main\\java\\com\\payroll\\system\\repository\\PayrollRepositoryImpl.java", "source_location": "L172"}, {"caller_nid": "payrollrepositoryimpl_payrollrepositoryimpl_fetchemployeedata", "callee": "setString", "source_file": "src\\main\\java\\com\\payroll\\system\\repository\\PayrollRepositoryImpl.java", "source_location": "L173"}, {"caller_nid": "payrollrepositoryimpl_payrollrepositoryimpl_fetchemployeedata", "callee": "setString", "source_file": "src\\main\\java\\com\\payroll\\system\\repository\\PayrollRepositoryImpl.java", "source_location": "L174"}, {"caller_nid": "payrollrepositoryimpl_payrollrepositoryimpl_fetchemployeedata", "callee": "setString", "source_file": "src\\main\\java\\com\\payroll\\system\\repository\\PayrollRepositoryImpl.java", "source_location": "L175"}, {"caller_nid": "payrollrepositoryimpl_payrollrepositoryimpl_fetchemployeedata", "callee": "executeQuery", "source_file": "src\\main\\java\\com\\payroll\\system\\repository\\PayrollRepositoryImpl.java", "source_location": "L177"}, {"caller_nid": "payrollrepositoryimpl_payrollrepositoryimpl_fetchemployeedata", "callee": "next", "source_file": "src\\main\\java\\com\\payroll\\system\\repository\\PayrollRepositoryImpl.java", "source_location": "L178"}, {"caller_nid": "payrollrepositoryimpl_payrollrepositoryimpl_fetchemployeedata", "callee": "printf", "source_file": "src\\main\\java\\com\\payroll\\system\\repository\\PayrollRepositoryImpl.java", "source_location": "L191"}, {"caller_nid": "payrollrepositoryimpl_payrollrepositoryimpl_fetchemployeedata", "callee": "getMessage", "source_file": "src\\main\\java\\com\\payroll\\system\\repository\\PayrollRepositoryImpl.java", "source_location": "L192"}, {"caller_nid": "payrollrepositoryimpl_payrollrepositoryimpl_openconnection", "callee": "getConnection", "source_file": "src\\main\\java\\com\\payroll\\system\\repository\\PayrollRepositoryImpl.java", "source_location": "L198"}, {"caller_nid": "payrollrepositoryimpl_payrollrepositoryimpl_mapemployee", "callee": "getString", "source_file": "src\\main\\java\\com\\payroll\\system\\repository\\PayrollRepositoryImpl.java", "source_location": "L203"}, {"caller_nid": "payrollrepositoryimpl_payrollrepositoryimpl_mapemployee", "callee": "getString", "source_file": "src\\main\\java\\com\\payroll\\system\\repository\\PayrollRepositoryImpl.java", "source_location": "L204"}, {"caller_nid": "payrollrepositoryimpl_payrollrepositoryimpl_mapemployee", "callee": "getString", "source_file": "src\\main\\java\\com\\payroll\\system\\repository\\PayrollRepositoryImpl.java", "source_location": "L205"}, {"caller_nid": "payrollrepositoryimpl_payrollrepositoryimpl_mapemployee", "callee": "getInt", "source_file": "src\\main\\java\\com\\payroll\\system\\repository\\PayrollRepositoryImpl.java", "source_location": "L206"}, {"caller_nid": "payrollrepositoryimpl_payrollrepositoryimpl_mapemployee", "callee": "wasNull", "source_file": "src\\main\\java\\com\\payroll\\system\\repository\\PayrollRepositoryImpl.java", "source_location": "L207"}, {"caller_nid": "payrollrepositoryimpl_payrollrepositoryimpl_mapemployee", "callee": "getString", "source_file": "src\\main\\java\\com\\payroll\\system\\repository\\PayrollRepositoryImpl.java", "source_location": "L208"}, {"caller_nid": "payrollrepositoryimpl_payrollrepositoryimpl_mapemployee", "callee": "getDouble", "source_file": "src\\main\\java\\com\\payroll\\system\\repository\\PayrollRepositoryImpl.java", "source_location": "L209"}, {"caller_nid": "payrollrepositoryimpl_payrollrepositoryimpl_mapemployee", "callee": "getInt", "source_file": "src\\main\\java\\com\\payroll\\system\\repository\\PayrollRepositoryImpl.java", "source_location": "L210"}, {"caller_nid": "payrollrepositoryimpl_payrollrepositoryimpl_mapattendance", "callee": "getInt", "source_file": "src\\main\\java\\com\\payroll\\system\\repository\\PayrollRepositoryImpl.java", "source_location": "L216"}, {"caller_nid": "payrollrepositoryimpl_payrollrepositoryimpl_mapattendance", "callee": "getInt", "source_file": "src\\main\\java\\com\\payroll\\system\\repository\\PayrollRepositoryImpl.java", "source_location": "L217"}, {"caller_nid": "payrollrepositoryimpl_payrollrepositoryimpl_mapattendance", "callee": "getInt", "source_file": "src\\main\\java\\com\\payroll\\system\\repository\\PayrollRepositoryImpl.java", "source_location": "L218"}, {"caller_nid": "payrollrepositoryimpl_payrollrepositoryimpl_mapattendance", "callee": "getDouble", "source_file": "src\\main\\java\\com\\payroll\\system\\repository\\PayrollRepositoryImpl.java", "source_location": "L219"}, {"caller_nid": "payrollrepositoryimpl_payrollrepositoryimpl_mapfinancials", "callee": "getDouble", "source_file": "src\\main\\java\\com\\payroll\\system\\repository\\PayrollRepositoryImpl.java", "source_location": "L226"}, {"caller_nid": "payrollrepositoryimpl_payrollrepositoryimpl_mapfinancials", "callee": "getDouble", "source_file": "src\\main\\java\\com\\payroll\\system\\repository\\PayrollRepositoryImpl.java", "source_location": "L227"}, {"caller_nid": "payrollrepositoryimpl_payrollrepositoryimpl_mapfinancials", "callee": "getDouble", "source_file": "src\\main\\java\\com\\payroll\\system\\repository\\PayrollRepositoryImpl.java", "source_location": "L228"}, {"caller_nid": "payrollrepositoryimpl_payrollrepositoryimpl_mapfinancials", "callee": "getDouble", "source_file": "src\\main\\java\\com\\payroll\\system\\repository\\PayrollRepositoryImpl.java", "source_location": "L229"}, {"caller_nid": "payrollrepositoryimpl_payrollrepositoryimpl_maptaxcontext", "callee": "getString", "source_file": "src\\main\\java\\com\\payroll\\system\\repository\\PayrollRepositoryImpl.java", "source_location": "L235"}, {"caller_nid": "payrollrepositoryimpl_payrollrepositoryimpl_maptaxcontext", "callee": "getString", "source_file": "src\\main\\java\\com\\payroll\\system\\repository\\PayrollRepositoryImpl.java", "source_location": "L235"}, {"caller_nid": "payrollrepositoryimpl_payrollrepositoryimpl_maptaxcontext", "callee": "getString", "source_file": "src\\main\\java\\com\\payroll\\system\\repository\\PayrollRepositoryImpl.java", "source_location": "L236"}, {"caller_nid": "payrollrepositoryimpl_payrollrepositoryimpl_maptaxcontext", "callee": "getString", "source_file": "src\\main\\java\\com\\payroll\\system\\repository\\PayrollRepositoryImpl.java", "source_location": "L236"}, {"caller_nid": "payrollrepositoryimpl_payrollrepositoryimpl_maptaxcontext", "callee": "getString", "source_file": "src\\main\\java\\com\\payroll\\system\\repository\\PayrollRepositoryImpl.java", "source_location": "L237"}, {"caller_nid": "payrollrepositoryimpl_payrollrepositoryimpl_maptaxcontext", "callee": "getString", "source_file": "src\\main\\java\\com\\payroll\\system\\repository\\PayrollRepositoryImpl.java", "source_location": "L237"}, {"caller_nid": "payrollrepositoryimpl_payrollrepositoryimpl_maptaxcontext", "callee": "getString", "source_file": "src\\main\\java\\com\\payroll\\system\\repository\\PayrollRepositoryImpl.java", "source_location": "L238"}, {"caller_nid": "payrollrepositoryimpl_payrollrepositoryimpl_maptaxcontext", "callee": "getString", "source_file": "src\\main\\java\\com\\payroll\\system\\repository\\PayrollRepositoryImpl.java", "source_location": "L238"}, {"caller_nid": "payrollrepositoryimpl_payrollrepositoryimpl_maptaxcontext", "callee": "getString", "source_file": "src\\main\\java\\com\\payroll\\system\\repository\\PayrollRepositoryImpl.java", "source_location": "L239"}, {"caller_nid": "payrollrepositoryimpl_payrollrepositoryimpl_maptaxcontext", "callee": "getString", "source_file": "src\\main\\java\\com\\payroll\\system\\repository\\PayrollRepositoryImpl.java", "source_location": "L239"}, {"caller_nid": "payrollrepositoryimpl_payrollrepositoryimpl_maptaxcontext", "callee": "getString", "source_file": "src\\main\\java\\com\\payroll\\system\\repository\\PayrollRepositoryImpl.java", "source_location": "L240"}, {"caller_nid": "payrollrepositoryimpl_payrollrepositoryimpl_maptaxcontext", "callee": "getString", "source_file": "src\\main\\java\\com\\payroll\\system\\repository\\PayrollRepositoryImpl.java", "source_location": "L240"}, {"caller_nid": "payrollrepositoryimpl_payrollrepositoryimpl_maptaxcontext", "callee": "getString", "source_file": "src\\main\\java\\com\\payroll\\system\\repository\\PayrollRepositoryImpl.java", "source_location": "L242"}, {"caller_nid": "payrollrepositoryimpl_payrollrepositoryimpl_maptaxcontext", "callee": "getString", "source_file": "src\\main\\java\\com\\payroll\\system\\repository\\PayrollRepositoryImpl.java", "source_location": "L243"}, {"caller_nid": "payrollrepositoryimpl_payrollrepositoryimpl_coalesce", "callee": "isBlank", "source_file": "src\\main\\java\\com\\payroll\\system\\repository\\PayrollRepositoryImpl.java", "source_location": "L250"}, {"caller_nid": "payrollrepositoryimpl_payrollrepositoryimpl_ensurepayrollresultstable", "callee": "createStatement", "source_file": "src\\main\\java\\com\\payroll\\system\\repository\\PayrollRepositoryImpl.java", "source_location": "L258"}, {"caller_nid": "payrollrepositoryimpl_payrollrepositoryimpl_ensurepayrollresultstable", "callee": "execute", "source_file": "src\\main\\java\\com\\payroll\\system\\repository\\PayrollRepositoryImpl.java", "source_location": "L259"}, {"caller_nid": "payrollrepositoryimpl_payrollrepositoryimpl_ensurepayrollaudittable", "callee": "createStatement", "source_file": "src\\main\\java\\com\\payroll\\system\\repository\\PayrollRepositoryImpl.java", "source_location": "L278"}, {"caller_nid": "payrollrepositoryimpl_payrollrepositoryimpl_ensurepayrollaudittable", "callee": "execute", "source_file": "src\\main\\java\\com\\payroll\\system\\repository\\PayrollRepositoryImpl.java", "source_location": "L279"}, {"caller_nid": "payrollrepositoryimpl_payrollrepositoryimpl_gettablecolumns", "callee": "createStatement", "source_file": "src\\main\\java\\com\\payroll\\system\\repository\\PayrollRepositoryImpl.java", "source_location": "L294"}, {"caller_nid": "payrollrepositoryimpl_payrollrepositoryimpl_gettablecolumns", "callee": "executeQuery", "source_file": "src\\main\\java\\com\\payroll\\system\\repository\\PayrollRepositoryImpl.java", "source_location": "L295"}, {"caller_nid": "payrollrepositoryimpl_payrollrepositoryimpl_gettablecolumns", "callee": "next", "source_file": "src\\main\\java\\com\\payroll\\system\\repository\\PayrollRepositoryImpl.java", "source_location": "L296"}, {"caller_nid": "payrollrepositoryimpl_payrollrepositoryimpl_gettablecolumns", "callee": "add", "source_file": "src\\main\\java\\com\\payroll\\system\\repository\\PayrollRepositoryImpl.java", "source_location": "L297"}, {"caller_nid": "payrollrepositoryimpl_payrollrepositoryimpl_gettablecolumns", "callee": "toLowerCase", "source_file": "src\\main\\java\\com\\payroll\\system\\repository\\PayrollRepositoryImpl.java", "source_location": "L297"}, {"caller_nid": "payrollrepositoryimpl_payrollrepositoryimpl_gettablecolumns", "callee": "getString", "source_file": "src\\main\\java\\com\\payroll\\system\\repository\\PayrollRepositoryImpl.java", "source_location": "L297"}, {"caller_nid": "payrollrepositoryimpl_payrollrepositoryimpl_putifpresent", "callee": "contains", "source_file": "src\\main\\java\\com\\payroll\\system\\repository\\PayrollRepositoryImpl.java", "source_location": "L305"}, {"caller_nid": "payrollrepositoryimpl_payrollrepositoryimpl_putifpresent", "callee": "toLowerCase", "source_file": "src\\main\\java\\com\\payroll\\system\\repository\\PayrollRepositoryImpl.java", "source_location": "L305"}, {"caller_nid": "payrollrepositoryimpl_payrollrepositoryimpl_putifpresent", "callee": "put", "source_file": "src\\main\\java\\com\\payroll\\system\\repository\\PayrollRepositoryImpl.java", "source_location": "L306"}, {"caller_nid": "payrollrepositoryimpl_payrollrepositoryimpl_buildinsertsql", "callee": "join", "source_file": "src\\main\\java\\com\\payroll\\system\\repository\\PayrollRepositoryImpl.java", "source_location": "L313"}, {"caller_nid": "payrollrepositoryimpl_payrollrepositoryimpl_buildinsertsql", "callee": "keySet", "source_file": "src\\main\\java\\com\\payroll\\system\\repository\\PayrollRepositoryImpl.java", "source_location": "L313"}, {"caller_nid": "payrollrepositoryimpl_payrollrepositoryimpl_buildinsertsql", "callee": "join", "source_file": "src\\main\\java\\com\\payroll\\system\\repository\\PayrollRepositoryImpl.java", "source_location": "L314"}, {"caller_nid": "payrollrepositoryimpl_payrollrepositoryimpl_buildinsertsql", "callee": "nCopies", "source_file": "src\\main\\java\\com\\payroll\\system\\repository\\PayrollRepositoryImpl.java", "source_location": "L314"}, {"caller_nid": "payrollrepositoryimpl_payrollrepositoryimpl_buildinsertsql", "callee": "size", "source_file": "src\\main\\java\\com\\payroll\\system\\repository\\PayrollRepositoryImpl.java", "source_location": "L314"}]}